webhooklib/__init__.py
webhooklib/client.py
webhooklib/config.py
webhooklib/dependencies.py
webhooklib/exceptions.py
webhooklib/models.py
webhooklib/pipeline.py
webhooklib/process_wrapper.py
webhooklib/run.py
webhooklib/server.py
webhooklib-0.11.8.dist-info/METADATA
webhooklib-0.11.8.dist-info/WHEEL
webhooklib-0.11.8.dist-info/top_level.txt
webhooklib-0.11.8.dist-info/RECORD
