Metadata-Version: 2.1
Name: webhooklib
Version: 0.11.8
Summary: tool for remote process call
Author-email: Alexander Rodionov <tandav@tandav.me>
Project-URL: source, https://github.com/tandav/webhook
Project-URL: issues, https://tandav.github.io/webhook/issues
Project-URL: release notes, https://tandav.github.io/webhook/releases
Requires-Python: >=3.10
Requires-Dist: fastapi
Requires-Dist: uvicorn
Requires-Dist: redis
Requires-Dist: requests
Requires-Dist: pydantic
Requires-Dist: colorama
Provides-Extra: dev
Requires-Dist: bumpver ; extra == 'dev'
Requires-Dist: pre-commit ; extra == 'dev'
Requires-Dist: pytest ; extra == 'dev'
